Tool.py
zzhtestlib/__init__.py
zzhtestlib/zzhlibone.py
zzhtestlib-1.0.0.dist-info/LICENSE.txt
zzhtestlib-1.0.0.dist-info/METADATA
zzhtestlib-1.0.0.dist-info/WHEEL
zzhtestlib-1.0.0.dist-info/top_level.txt
zzhtestlib-1.0.0.dist-info/RECORD
