Metadata-Version: 2.1
Name: zzhtestlib
Version: 1.0.0
Summary: this is a niu lib
Home-page: https://github/wangshi
Author: zzh
Author-email: 1004923690@qq.com
License: MIT
Platform: UNKNOWN
